LICENSE.txt
MANIFEST.in
README.rst
setup.py
bin/httproxy
src/httproxy.py
src/httproxy.egg-info/PKG-INFO
src/httproxy.egg-info/SOURCES.txt
src/httproxy.egg-info/dependency_links.txt
src/httproxy.egg-info/not-zip-safe
src/httproxy.egg-info/requires.txt
src/httproxy.egg-info/top_level.txt